deepsight/__init__.py
deepsight/kaggle_sight.py
deepsight/kaggle_explorer/__init__.py
deepsight/kaggle_explorer/dicom_copy_machine.py
deepsight/kaggle_explorer/dicom_data_fixer.py
gp2/__init__.py
gp2/__version__.py
gp2/runner.py
gp2/data/__init__.py
gp2/data/collection.py
gp2/data/data_converter.py
gp2/data/manager.py
gp2/data/point.py
gp2/gp2/__init__.py
gp2/gp2/util.py
gp2/gp2/classifiers/__init__.py
gp2/gp2/classifiers/base_keras_segmentation_classifier.py
gp2/gp2/classifiers/classifier.py
gp2/gp2/classifiers/k_att_unet2d.py
gp2/gp2/classifiers/k_r2_unet2d.py
gp2/gp2/classifiers/k_res_unet2d.py
gp2/gp2/classifiers/k_unet.py
gp2/gp2/classifiers/k_unet2d.py
gp2/gp2/classifiers/k_unet3_plus2d.py
gp2/gp2/classifiers/k_unet_plus2d.py
gp2/gp2/classifiers/k_vnet2d.py
gp2/gp2/classifiers/unet.py
gp2/gp2/classifiers/unet_plus.py
gp2/gp2/discriminators/__init__.py
gp2/gp2/discriminators/base_cnn_discriminator.py
gp2/gp2/discriminators/cnn_discriminator_plus.py
gp2/gp2/discriminators/cnndiscriminator.py
gp2/gp2/discriminators/discriminator.py
gp2-0.7.22.23.dist-info/LICENSE
gp2-0.7.22.23.dist-info/METADATA
gp2-0.7.22.23.dist-info/WHEEL
gp2-0.7.22.23.dist-info/top_level.txt
gp2-0.7.22.23.dist-info/RECORD
